hotpdf/__init__.py
hotpdf/hotpdf.py
hotpdf/memory_map.py
hotpdf/processor.py
hotpdf/span_map.py
hotpdf/sparse_matrix.py
hotpdf/trie.py
hotpdf/utils.py
hotpdf/data/__init__.py
hotpdf/data/classes.py
hotpdf/exceptions/__init__.py
hotpdf/exceptions/custom_exceptions.py
hotpdf-0.5.2.dist-info/LICENSE
hotpdf-0.5.2.dist-info/METADATA
hotpdf-0.5.2.dist-info/WHEEL
hotpdf-0.5.2.dist-info/top_level.txt
hotpdf-0.5.2.dist-info/RECORD
