Metadata-Version: 2.1
Name: hotpdf
Version: 0.5.2
Summary: Fast PDF Data Extraction library
Author-email: Krishnasis Mandal <krishnasis.mandal@prestatech.com>
Maintainer-email: Alex Ptakhin <alex.ptakhin@prestatech.com>, Izel Odabasi <izel.odabasi@prestatech.com>, Mattia Callegari <callegari.mattia@protonmail.com>
License: MIT License
Keywords: pdf,data extraction,text extraction,hotpdf,pdfminer,pdfquery
Classifier: License :: OSI Approved :: MIT License
Classifier: Programming Language :: Python :: 3.11
Classifier: Programming Language :: Python :: 3.10
Classifier: Programming Language :: Python :: 3.9
Classifier: Development Status :: 4 - Beta
Classifier: Intended Audience :: Developers
Classifier: Topic :: Software Development :: Libraries :: Python Modules
Classifier: Topic :: Text Processing :: General
Classifier: Topic :: Text Processing :: Indexing
Classifier: Topic :: Text Processing :: Linguistic
Classifier: Topic :: Utilities
Classifier: Operating System :: OS Independent
Requires-Python: >=3.9
License-File: LICENSE
Requires-Dist: pdfminer.six >=20231228
Provides-Extra: dev
Requires-Dist: pytest ; extra == 'dev'
Requires-Dist: pytest-cov ; extra == 'dev'
Requires-Dist: pytest-xdist ; extra == 'dev'
Requires-Dist: pylint ; extra == 'dev'
Requires-Dist: mypy ; extra == 'dev'
Requires-Dist: typing-extensions ; extra == 'dev'
Requires-Dist: pre-commit ; extra == 'dev'
Requires-Dist: ruff ; extra == 'dev'
Provides-Extra: docs
Requires-Dist: pdfminer.six ; extra == 'docs'
